{"title":"重庆市公考雷达","url":"https://www.gongkaoleida.com/area/2460-2461-0-2,3,59,78-124","favicon":"https://www.gongkaoleida.com/favicon.ico","elements":[{"contents":"<!--公告列表-->\n                <div class=\"notice-list\">\n                    <ul class=\"link-list\">\n                                                    <li>\n                                <h5>\n                                    <i class=\"notice-label\">[重庆市]</i>\n                                    <i class=\"notice-label\">[国企]</i>\n                                    \n                                    <a href=\"https://www.gongkaoleida.com/article/1753392\" target=\"_blank\" title=\"重庆机电智能制造有限公司招聘简章\">重庆机电智能制造有限公司招聘简章</a>\n                                </h5>\n                                <time class=\" time-red \">3小时前</time>\n                            </li>\n                                                    <li>\n                                <h5>\n                                    <i class=\"notice-label\">[沙坪坝区]</i>\n                                    <i class=\"notice-label\">[事业单位]</i>\n                                    \n                                    <a href=\"https://www.gongkaoleida.com/article/1753151\" target=\"_blank\" title=\"重庆大学自动化学院国际期刊劳务派遣助理招聘启事\">重庆大学自动化学院国际期刊劳务派遣助理招聘启事</a>\n                                </h5>\n                                <time class=\" time-red \">4小时前</time>\n                            </li>\n                                                    <li>\n                                <h5>\n                                    <i class=\"notice-label\">[涪陵区]</i>\n                                    <i class=\"notice-label\">[事业单位]</i>\n                                    \n                                    <a href=\"https://www.gongkaoleida.com/article/1752793\" target=\"_blank\" title=\"重庆市涪陵区事业单位面向2023年服务期满且考核合格“三支一扶”人员公开招聘工作人员公告\">重庆市涪陵区事业单位面向2023年服务期满且考核合格“三支一扶”人员公开招聘工作人员公告</a>\n                                </h5>\n                                <time class=\"\">2023-12-16</time>\n                            </li>\n                                                    <li>\n                                <h5>\n                                    <i class=\"notice-label\">[巴南区]</i>\n                                    <i class=\"notice-label\">[事业单位]</i>\n                                    \n                                    <a href=\"https://www.gongkaoleida.com/article/1752428\" target=\"_blank\" title=\"公开招聘2023年巴南区消防救援支队消防宣传文员简章\">公开招聘2023年巴南区消防救援支队消防宣传文员简章</a>\n                                </h5>\n                                <time class=\"\">2023-12-16</time>\n                            </li>\n                                                    <li>\n                                <h5>\n                                    <i class=\"notice-label\">[渝北区]</i>\n                                    <i class=\"notice-label\">[国企]</i>\n                                    \n                                    <a href=\"https://www.gongkaoleida.com/article/1752085\" target=\"_blank\" title=\"重庆两江新区人才发展集团有限公司派往重庆云投信息技术有限公司外包岗位招聘简章\">重庆两江新区人才发展集团有限公司派往重庆云投信息技术有限公司外包岗位招聘简章</a>\n                                </h5>\n                                <time class=\"\">2023-12-15</time>\n                            </li>\n                                                    <li>\n                                <h5>\n                                    <i class=\"notice-label\">[重庆市]</i>\n                                    <i class=\"notice-label\">[事业单位]</i>\n                                    \n                                    <a href=\"https://www.gongkaoleida.com/article/1752084\" target=\"_blank\" title=\"重庆两江新区人才发展集团派往两江新区某机关单位派遣人员招聘简章\">重庆两江新区人才发展集团派往两江新区某机关单位派遣人员招聘简章</a>\n                                </h5>\n                                <time class=\"\">2023-12-15</time>\n                            </li>\n                                                    <li>\n                                <h5>\n                                    <i class=\"notice-label\">[南岸区]</i>\n                                    <i class=\"notice-label\">[事业单位]</i>\n                                    \n                                    <a href=\"https://www.gongkaoleida.com/article/1751958\" target=\"_blank\" title=\"重庆第二师范学院关于招聘专家研究助理的公告\">重庆第二师范学院关于招聘专家研究助理的公告</a>\n                                </h5>\n                                <time class=\"\">2023-12-15</time>\n                            </li>\n                                                    <li>\n                                <h5>\n                                    <i class=\"notice-label\">[武隆区]</i>\n                                    <i class=\"notice-label\">[事业单位]</i>\n                                    \n                                    <a href=\"https://www.gongkaoleida.com/article/1751802\" target=\"_blank\" title=\"重庆市武隆区事业单位面向2022届服务期满且考核合格“三支一扶”人员公开招聘工作人员公告\">重庆市武隆区事业单位面向2022届服务期满且考核合格“三支一扶”人员公开招聘工作人员公告</a>\n                                </h5>\n                                <time class=\"\">2023-12-15</time>\n                            </li>\n                                                    <li>\n                                <h5>\n                                    <i class=\"notice-label\">[重庆市]</i>\n                                    <i class=\"notice-label\">[国企]</i>\n                                    \n                                    <a href=\"https://www.gongkaoleida.com/article/1751496\" target=\"_blank\" title=\"重庆九洲隆瓴科技有限公司关于招聘核算会计专员岗的公告\">重庆九洲隆瓴科技有限公司关于招聘核算会计专员岗的公告</a>\n                                </h5>\n                                <time class=\"\">2023-12-15</time>\n                            </li>\n                                                    <li>\n                                <h5>\n                                    <i class=\"notice-label\">[江北区]</i>\n                                    <i class=\"notice-label\">[国企]</i>\n                                    \n                                    <a href=\"https://www.gongkaoleida.com/article/1751438\" target=\"_blank\" title=\"重庆市城投金卡信息产业(集团)股份有限公司关于法务部合规主管的招聘公告\">重庆市城投金卡信息产业(集团)股份有限公司关于法务部合规主管的招聘公告</a>\n                                </h5>\n                                <time class=\"\">2023-12-15</time>\n                            </li>\n                                                    <li>\n                                <h5>\n                                    <i class=\"notice-label\">[重庆市]</i>\n                                    <i class=\"notice-label\">[事业单位]</i>\n                                    \n                                    <a href=\"https://www.gongkaoleida.com/article/1751123\" target=\"_blank\" title=\"重庆大学计算机学院劳务派遣实验室助理招聘启事\">重庆大学计算机学院劳务派遣实验室助理招聘启事</a>\n                                </h5>\n                                <time class=\"\">2023-12-15</time>\n                            </li>\n                                                    <li>\n                                <h5>\n                                    <i class=\"notice-label\">[重庆市]</i>\n                                    <i class=\"notice-label\">[事业单位]</i>\n                                    \n                                    <a href=\"https://www.gongkaoleida.com/article/1751121\" target=\"_blank\" title=\"重庆大学马克思主义学院劳务派遣工作人员招聘启事\">重庆大学马克思主义学院劳务派遣工作人员招聘启事</a>\n                                </h5>\n                                <time class=\"\">2023-12-15</time>\n                            </li>\n                                                    <li>\n                                <h5>\n                                    <i class=\"notice-label\">[重庆市]</i>\n                                    <i class=\"notice-label\">[事业单位]</i>\n                                    \n                                    <a href=\"https://www.gongkaoleida.com/article/1751122\" target=\"_blank\" title=\"重庆大学生物工程学院学生办公室劳务派遣工作人员招聘启事\">重庆大学生物工程学院学生办公室劳务派遣工作人员招聘启事</a>\n                                </h5>\n                                <time class=\"\">2023-12-15</time>\n                            </li>\n                                                    <li>\n                                <h5>\n                                    <i class=\"notice-label\">[巫溪县]</i>\n                                    <i class=\"notice-label\">[教师]</i>\n                                    \n                                    <a href=\"https://www.gongkaoleida.com/article/1750822\" target=\"_blank\" title=\"重庆市巫溪县教育事业单位2023年面向特岗教师公开招聘工作人员公告\">重庆市巫溪县教育事业单位2023年面向特岗教师公开招聘工作人员公告</a>\n                                </h5>\n                                <time class=\"\">2023-12-15</time>\n                            </li>\n                                                    <li>\n                                <h5>\n                                    <i class=\"notice-label\">[江北区]</i>\n                                    <i class=\"notice-label\">[国企]</i>\n                                    \n                                    <a href=\"https://www.gongkaoleida.com/article/1750638\" target=\"_blank\" title=\"重庆江北国际机场有限公司社会招聘简章\">重庆江北国际机场有限公司社会招聘简章</a>\n                                </h5>\n                                <time class=\"\">2023-12-14</time>\n                            </li>\n                                                    <li>\n                                <h5>\n                                    <i class=\"notice-label\">[重庆市]</i>\n                                    <i class=\"notice-label\">[国企]</i>\n                                    \n                                    <a href=\"https://www.gongkaoleida.com/article/1750630\" target=\"_blank\" title=\"重庆农投良食品集团有限公司招聘信息\">重庆农投良食品集团有限公司招聘信息</a>\n                                </h5>\n                                <time class=\"\">2023-12-14</time>\n                            </li>\n                                                    <li>\n                                <h5>\n                                    <i class=\"notice-label\">[云阳县]</i>\n                                    <i class=\"notice-label\">[国企]</i>\n                                    \n                                    <a href=\"https://www.gongkaoleida.com/article/1749966\" target=\"_blank\" title=\"云阳县云畅实业集团有限责任公司公开招聘公告\">云阳县云畅实业集团有限责任公司公开招聘公告</a>\n                                </h5>\n                                <time class=\"\">2023-12-14</time>\n                            </li>\n                                                    <li>\n                                <h5>\n                                    <i class=\"notice-label\">[重庆市]</i>\n                                    <i class=\"notice-label\">[国企]</i>\n                                    \n                                    <a href=\"https://www.gongkaoleida.com/article/1749951\" target=\"_blank\" title=\"重庆建工第二建设有限公司招聘启事\">重庆建工第二建设有限公司招聘启事</a>\n                                </h5>\n                                <time class=\"\">2023-12-14</time>\n                            </li>\n                                                    <li>\n                                <h5>\n                                    <i class=\"notice-label\">[重庆市]</i>\n                                    <i class=\"notice-label\">[教师]</i>\n                                    \n                                    <a href=\"https://www.gongkaoleida.com/article/1749580\" target=\"_blank\" title=\"重庆大学外国语学院2024年春季学期驻校博士生招聘启事\">重庆大学外国语学院2024年春季学期驻校博士生招聘启事</a>\n                                </h5>\n                                <time class=\"\">2023-12-14</time>\n                            </li>\n                                                    <li>\n                                <h5>\n                                    <i class=\"notice-label\">[渝中区]</i>\n                                    <i class=\"notice-label\">[事业单位]</i>\n                                    \n                                    <a href=\"https://www.gongkaoleida.com/article/1749282\" target=\"_blank\" title=\"重庆医科大学附属第一医院关于重医附一院审计处招聘1名编外工作人员的通知\">重庆医科大学附属第一医院关于重医附一院审计处招聘1名编外工作人员的通知</a>\n                                </h5>\n                                <time class=\"\">2023-12-13</time>\n                            </li>\n                                                    <li>\n                                <h5>\n                                    <i class=\"notice-label\">[铜梁区]</i>\n                                    <i class=\"notice-label\">[国企]</i>\n                                    \n                                    <a href=\"https://www.gongkaoleida.com/article/1749143\" target=\"_blank\" title=\"重庆市铜梁区保安服务有限公司关于公开招聘行政事务文员的启事\">重庆市铜梁区保安服务有限公司关于公开招聘行政事务文员的启事</a>\n                                </h5>\n                                <time class=\"\">2023-12-13</time>\n                            </li>\n                                                    <li>\n                                <h5>\n                                    <i class=\"notice-label\">[合川区]</i>\n                                    <i class=\"notice-label\">[事业单位]</i>\n                                    \n                                    <a href=\"https://www.gongkaoleida.com/article/1748517\" target=\"_blank\" title=\"重庆精诚企业管理有限公司派往合川区公安局警务辅助岗位工作人员招聘公告\">重庆精诚企业管理有限公司派往合川区公安局警务辅助岗位工作人员招聘公告</a>\n                                </h5>\n                                <time class=\"\">2023-12-13</time>\n                            </li>\n                                                    <li>\n                                <h5>\n                                    <i class=\"notice-label\">[重庆市]</i>\n                                    <i class=\"notice-label\">[教师]</i>\n                                    \n                                    <a href=\"https://www.gongkaoleida.com/article/1748470\" target=\"_blank\" title=\"重庆大学人文社会科学高等研究院&amp;博雅学院中文系2024年教师招聘启事\">重庆大学人文社会科学高等研究院&amp;博雅学院中文系2024年教师招聘启事</a>\n                                </h5>\n                                <time class=\"\">2023-12-13</time>\n                            </li>\n                                                    <li>\n                                <h5>\n                                    <i class=\"notice-label\">[重庆市]</i>\n                                    <i class=\"notice-label\">[教师]</i>\n                                    \n                                    <a href=\"https://www.gongkaoleida.com/article/1748469\" target=\"_blank\" title=\"重庆大学人文社会科学高等研究院&amp;博雅学院哲学系2024年教师招聘启事\">重庆大学人文社会科学高等研究院&amp;博雅学院哲学系2024年教师招聘启事</a>\n                                </h5>\n                                <time class=\"\">2023-12-13</time>\n                            </li>\n                                                    <li>\n                                <h5>\n                                    <i class=\"notice-label\">[渝北区]</i>\n                                    <i class=\"notice-label\">[教师]</i>\n                                    \n                                    <a href=\"https://www.gongkaoleida.com/article/1747380\" target=\"_blank\" title=\"渝北区回兴幼儿园招聘启事\">渝北区回兴幼儿园招聘启事</a>\n                                </h5>\n                                <time class=\"\">2023-12-12</time>\n                            </li>\n                                                    <li>\n                                <h5>\n                                    <i class=\"notice-label\">[永川区]</i>\n                                    <i class=\"notice-label\">[教师]</i>\n                                    \n                                    <a href=\"https://www.gongkaoleida.com/article/1746727\" target=\"_blank\" title=\"重庆财经职业学院2024年第一季度非事业编制工作人员招聘简章\">重庆财经职业学院2024年第一季度非事业编制工作人员招聘简章</a>\n                                </h5>\n                                <time class=\"\">2023-12-12</time>\n                            </li>\n                                                    <li>\n                                <h5>\n                                    <i class=\"notice-label\">[重庆市]</i>\n                                    <i class=\"notice-label\">[国企]</i>\n                                    \n                                    <a href=\"https://www.gongkaoleida.com/article/1746505\" target=\"_blank\" title=\"西南证券公司招聘公告\">西南证券公司招聘公告</a>\n                                </h5>\n                                <time class=\"\">2023-12-12</time>\n                            </li>\n                                                    <li>\n                                <h5>\n                                    <i class=\"notice-label\">[重庆市]</i>\n                                    <i class=\"notice-label\">[国企]</i>\n                                    \n                                    <a href=\"https://www.gongkaoleida.com/article/1746434\" target=\"_blank\" title=\"重庆航运建设发展(集团)有限公司招聘公告\">重庆航运建设发展(集团)有限公司招聘公告</a>\n                                </h5>\n                                <time class=\"\">2023-12-12</time>\n                            </li>\n                                                    <li>\n                                <h5>\n                                    <i class=\"notice-label\">[重庆市]</i>\n                                    <i class=\"notice-label\">[国企]</i>\n                                    \n                                    <a href=\"https://www.gongkaoleida.com/article/1746433\" target=\"_blank\" title=\"民生集团及所属子公司公开招聘简章\">民生集团及所属子公司公开招聘简章</a>\n                                </h5>\n                                <time class=\"\">2023-12-12</time>\n                            </li>\n                                                    <li>\n                                <h5>\n                                    <i class=\"notice-label\">[渝中区]</i>\n                                    <i class=\"notice-label\">[教师]</i>\n                                    \n                                    <a href=\"https://www.gongkaoleida.com/article/1745431\" target=\"_blank\" title=\"重庆医科大学编外聘用人员招聘简章(2023年第11轮)\">重庆医科大学编外聘用人员招聘简章(2023年第11轮)</a>\n                                </h5>\n                                <time class=\"\">2023-12-11</time>\n                            </li>\n                                            </ul>\n                </div>\n                <div class=\"pagelist-box\">\n    <ul class=\"pagelist clearfix\">\n\n                    <li class=\"disabled\"><a href=\"javascript:;\">首页</a></li>\n            <li class=\"disabled\"><a href=\"javascript:;\">上一页</a></li>\n        \n                    <li><a href=\"/area/2460-2461-0-2,3,59,78-124?page=1\" class=\"list-num  list-active \">1</a></li>\n                    <li><a href=\"/area/2460-2461-0-2,3,59,78-124?page=2\" class=\"list-num \">2</a></li>\n                    <li><a href=\"/area/2460-2461-0-2,3,59,78-124?page=3\" class=\"list-num \">3</a></li>\n                    <li><a href=\"/area/2460-2461-0-2,3,59,78-124?page=4\" class=\"list-num \">4</a></li>\n                    <li><a href=\"/area/2460-2461-0-2,3,59,78-124?page=5\" class=\"list-num \">5</a></li>\n                    <li><a href=\"/area/2460-2461-0-2,3,59,78-124?page=6\" class=\"list-num \">6</a></li>\n                    <li><a href=\"/area/2460-2461-0-2,3,59,78-124?page=7\" class=\"list-num \">7</a></li>\n        \n                    <li class=\"pagelist-ellipsis\"><span>···</span></li>\n            <li><a href=\"/area/2460-2461-0-2,3,59,78-124?page=228\" class=\"list-num\">228</a></li>\n        \n                    <li><a href=\"/area/2460-2461-0-2,3,59,78-124?page=2\">下一页</a></li>\n            <li><a href=\"/area/2460-2461-0-2,3,59,78-124?page=228\">尾页</a></li>\n        \n    </ul>\n</div>","link":"https://www.gongkaoleida.com/article/1753392","retrieved":1702877579637}]}