{"title":"重庆市公考雷达","url":"https://www.gongkaoleida.com/area/2460-2461-0-2,3,59,78-124","favicon":"https://www.gongkaoleida.com/favicon.ico","elements":[{"contents":"<!--公告列表-->\n                <div class=\"notice-list\">\n                    <ul class=\"link-list\">\n                                                    <li>\n                                <h5>\n                                    <i class=\"notice-label\">[渝中区]</i>\n                                    <i class=\"notice-label\">[事业单位]</i>\n                                    \n                                    <a href=\"https://www.gongkaoleida.com/article/1615047\" target=\"_blank\" title=\"重庆医科大学附属第一医院关于重医附一院生殖医学中心招聘1名编外秘书的通知\">重庆医科大学附属第一医院关于重医附一院生殖医学中心招聘1名编外秘书的通知</a>\n                                </h5>\n                                <time class=\" time-red \">3小时前</time>\n                            </li>\n                                                    <li>\n                                <h5>\n                                    <i class=\"notice-label\">[渝中区]</i>\n                                    <i class=\"notice-label\">[事业单位]</i>\n                                    \n                                    <a href=\"https://www.gongkaoleida.com/article/1615048\" target=\"_blank\" title=\"重庆医科大学附属第一医院关于重医附一院临床营养科招聘1名编外秘书的通知\">重庆医科大学附属第一医院关于重医附一院临床营养科招聘1名编外秘书的通知</a>\n                                </h5>\n                                <time class=\" time-red \">3小时前</time>\n                            </li>\n                                                    <li>\n                                <h5>\n                                    <i class=\"notice-label\">[渝中区]</i>\n                                    <i class=\"notice-label\">[事业单位]</i>\n                                    \n                                    <a href=\"https://www.gongkaoleida.com/article/1614894\" target=\"_blank\" title=\"关于重医一院医务处招聘1名编外工作人员的通知\">关于重医一院医务处招聘1名编外工作人员的通知</a>\n                                </h5>\n                                <time class=\" time-red \">3小时前</time>\n                            </li>\n                                                    <li>\n                                <h5>\n                                    <i class=\"notice-label\">[九龙坡区]</i>\n                                    <i class=\"notice-label\">[教师]</i>\n                                    \n                                    <a href=\"https://www.gongkaoleida.com/article/1614851\" target=\"_blank\" title=\"重庆市育才中学校2023年教师招聘启事\">重庆市育才中学校2023年教师招聘启事</a>\n                                </h5>\n                                <time class=\" time-red \">4小时前</time>\n                            </li>\n                                                    <li>\n                                <h5>\n                                    <i class=\"notice-label\">[梁平区]</i>\n                                    <i class=\"notice-label\">[教师]</i>\n                                    \n                                    <a href=\"https://www.gongkaoleida.com/article/1614146\" target=\"_blank\" title=\"重庆市梁平区教育事业单位面向2023届公费师范生公开招聘工作人员公告\">重庆市梁平区教育事业单位面向2023届公费师范生公开招聘工作人员公告</a>\n                                </h5>\n                                <time class=\" time-red \">20小时前</time>\n                            </li>\n                                                    <li>\n                                <h5>\n                                    <i class=\"notice-label\">[重庆市]</i>\n                                    <i class=\"notice-label\">[国企]</i>\n                                    \n                                    <a href=\"https://www.gongkaoleida.com/article/1613585\" target=\"_blank\" title=\"重庆市大高农业发展有限公司招聘简章\">重庆市大高农业发展有限公司招聘简章</a>\n                                </h5>\n                                <time class=\" time-red \">22小时前</time>\n                            </li>\n                                                    <li>\n                                <h5>\n                                    <i class=\"notice-label\">[渝北区]</i>\n                                    <i class=\"notice-label\">[事业单位]</i>\n                                    \n                                    <a href=\"https://www.gongkaoleida.com/article/1613494\" target=\"_blank\" title=\"渝北区政协办公室招聘工作人员简章\">渝北区政协办公室招聘工作人员简章</a>\n                                </h5>\n                                <time class=\" time-red \">22小时前</time>\n                            </li>\n                                                    <li>\n                                <h5>\n                                    <i class=\"notice-label\">[南川区]</i>\n                                    <i class=\"notice-label\">[教师]</i>\n                                    \n                                    <a href=\"https://www.gongkaoleida.com/article/1613267\" target=\"_blank\" title=\"隆化职中2023年下半年面向社会公开招聘非编聘用人员简章\">隆化职中2023年下半年面向社会公开招聘非编聘用人员简章</a>\n                                </h5>\n                                <time class=\" time-red \">23小时前</time>\n                            </li>\n                                                    <li>\n                                <h5>\n                                    <i class=\"notice-label\">[重庆市]</i>\n                                    <i class=\"notice-label\">[国企]</i>\n                                    \n                                    <a href=\"https://www.gongkaoleida.com/article/1613007\" target=\"_blank\" title=\"重庆航运建设发展（集团）有限公司招聘启事\">重庆航运建设发展（集团）有限公司招聘启事</a>\n                                </h5>\n                                <time class=\"\">2023-08-22</time>\n                            </li>\n                                                    <li>\n                                <h5>\n                                    <i class=\"notice-label\">[巴南区]</i>\n                                    <i class=\"notice-label\">[教师]</i>\n                                    \n                                    <a href=\"https://www.gongkaoleida.com/article/1612960\" target=\"_blank\" title=\"重庆文化艺术职业学院合同制英语专任教师招聘简章\">重庆文化艺术职业学院合同制英语专任教师招聘简章</a>\n                                </h5>\n                                <time class=\"\">2023-08-22</time>\n                            </li>\n                                                    <li>\n                                <h5>\n                                    <i class=\"notice-label\">[梁平区]</i>\n                                    <i class=\"notice-label\">[国企]</i>\n                                    \n                                    <a href=\"https://www.gongkaoleida.com/article/1612668\" target=\"_blank\" title=\"重庆广汇供电服务有限责任公司万州分公司2023年招聘公告\">重庆广汇供电服务有限责任公司万州分公司2023年招聘公告</a>\n                                </h5>\n                                <time class=\"\">2023-08-22</time>\n                            </li>\n                                                    <li>\n                                <h5>\n                                    <i class=\"notice-label\">[渝北区]</i>\n                                    <i class=\"notice-label\">[教师]</i>\n                                    \n                                    <a href=\"https://www.gongkaoleida.com/article/1612455\" target=\"_blank\" title=\"渝北区长安锦绣实验小学招聘启事\">渝北区长安锦绣实验小学招聘启事</a>\n                                </h5>\n                                <time class=\"\">2023-08-22</time>\n                            </li>\n                                                    <li>\n                                <h5>\n                                    <i class=\"notice-label\">[重庆市]</i>\n                                    <i class=\"notice-label\">[事业单位]</i>\n                                    \n                                    <a href=\"https://www.gongkaoleida.com/article/1611671\" target=\"_blank\" title=\"重庆市医师协会2023年招聘工作人员启事\">重庆市医师协会2023年招聘工作人员启事</a>\n                                </h5>\n                                <time class=\"\">2023-08-21</time>\n                            </li>\n                                                    <li>\n                                <h5>\n                                    <i class=\"notice-label\">[重庆市]</i>\n                                    <i class=\"notice-label\">[国企]</i>\n                                    \n                                    <a href=\"https://www.gongkaoleida.com/article/1611246\" target=\"_blank\" title=\"重庆航运建设发展(集团)有限公司招聘启事\">重庆航运建设发展(集团)有限公司招聘启事</a>\n                                </h5>\n                                <time class=\"\">2023-08-21</time>\n                            </li>\n                                                    <li>\n                                <h5>\n                                    <i class=\"notice-label\">[重庆市]</i>\n                                    <i class=\"notice-label\">[国企]</i>\n                                    \n                                    <a href=\"https://www.gongkaoleida.com/article/1611245\" target=\"_blank\" title=\"重庆川仪十七厂有限公司2023年校园招聘\">重庆川仪十七厂有限公司2023年校园招聘</a>\n                                </h5>\n                                <time class=\"\">2023-08-21</time>\n                            </li>\n                                                    <li>\n                                <h5>\n                                    <i class=\"notice-label\">[沙坪坝区]</i>\n                                    <i class=\"notice-label\">[事业单位]</i>\n                                    \n                                    <a href=\"https://www.gongkaoleida.com/article/1610941\" target=\"_blank\" title=\"重庆市第十一人民医院关于招聘心理咨询工作人员的启事\">重庆市第十一人民医院关于招聘心理咨询工作人员的启事</a>\n                                </h5>\n                                <time class=\"\">2023-08-21</time>\n                            </li>\n                                                    <li>\n                                <h5>\n                                    <i class=\"notice-label\">[渝北区]</i>\n                                    <i class=\"notice-label\">[事业单位]</i>\n                                    \n                                    <a href=\"https://www.gongkaoleida.com/article/1610595\" target=\"_blank\" title=\"西南政法大学科研处校内招聘启事\">西南政法大学科研处校内招聘启事</a>\n                                </h5>\n                                <time class=\"\">2023-08-21</time>\n                            </li>\n                                                    <li>\n                                <h5>\n                                    <i class=\"notice-label\">[渝北区]</i>\n                                    <i class=\"notice-label\">[教师]</i>\n                                    \n                                    <a href=\"https://www.gongkaoleida.com/article/1610550\" target=\"_blank\" title=\"渝北区第三实验小学校招聘简章\">渝北区第三实验小学校招聘简章</a>\n                                </h5>\n                                <time class=\"\">2023-08-21</time>\n                            </li>\n                                                    <li>\n                                <h5>\n                                    <i class=\"notice-label\">[重庆市]</i>\n                                    <i class=\"notice-label\">[国企]</i>\n                                    \n                                    <a href=\"https://www.gongkaoleida.com/article/1610136\" target=\"_blank\" title=\"两江新区人力资源公司派往重庆两江新区国有企业外包岗位招聘简章(2023年8月批次)\">两江新区人力资源公司派往重庆两江新区国有企业外包岗位招聘简章(2023年8月批次)</a>\n                                </h5>\n                                <time class=\"\">2023-08-21</time>\n                            </li>\n                                                    <li>\n                                <h5>\n                                    <i class=\"notice-label\">[渝北区]</i>\n                                    <i class=\"notice-label\">[教师]</i>\n                                    \n                                    <a href=\"https://www.gongkaoleida.com/article/1610047\" target=\"_blank\" title=\"渝北区玉峰山中学教师招聘简章\">渝北区玉峰山中学教师招聘简章</a>\n                                </h5>\n                                <time class=\"\">2023-08-21</time>\n                            </li>\n                                                    <li>\n                                <h5>\n                                    <i class=\"notice-label\">[渝北区]</i>\n                                    <i class=\"notice-label\">[教师]</i>\n                                    \n                                    <a href=\"https://www.gongkaoleida.com/article/1609761\" target=\"_blank\" title=\"渝北区宝圣湖幼儿园招聘启事\">渝北区宝圣湖幼儿园招聘启事</a>\n                                </h5>\n                                <time class=\"\">2023-08-21</time>\n                            </li>\n                                                    <li>\n                                <h5>\n                                    <i class=\"notice-label\">[重庆市]</i>\n                                    <i class=\"notice-label\">[事业单位]</i>\n                                    \n                                    <a href=\"https://www.gongkaoleida.com/article/1608772\" target=\"_blank\" title=\"两江新区人力资源公司派往某单位派遣人员招聘简章\">两江新区人力资源公司派往某单位派遣人员招聘简章</a>\n                                </h5>\n                                <time class=\"\">2023-08-18</time>\n                            </li>\n                                                    <li>\n                                <h5>\n                                    <i class=\"notice-label\">[忠县]</i>\n                                    <i class=\"notice-label\">[教师]</i>\n                                    \n                                    <a href=\"https://www.gongkaoleida.com/article/1608537\" target=\"_blank\" title=\"重庆市忠县2023年公开招聘教育事业单位工作人员公告\">重庆市忠县2023年公开招聘教育事业单位工作人员公告</a>\n                                </h5>\n                                <time class=\"\">2023-08-18</time>\n                            </li>\n                                                    <li>\n                                <h5>\n                                    <i class=\"notice-label\">[渝北区]</i>\n                                    <i class=\"notice-label\">[国企]</i>\n                                    \n                                    <a href=\"https://www.gongkaoleida.com/article/1608373\" target=\"_blank\" title=\"重庆交运科技有限公司招聘开发人员简章\">重庆交运科技有限公司招聘开发人员简章</a>\n                                </h5>\n                                <time class=\"\">2023-08-18</time>\n                            </li>\n                                                    <li>\n                                <h5>\n                                    <i class=\"notice-label\">[重庆市]</i>\n                                    <i class=\"notice-label\">[国企]</i>\n                                    \n                                    <a href=\"https://www.gongkaoleida.com/article/1608326\" target=\"_blank\" title=\"数字重庆信息技术服务有限公司2023年市场化招聘专业人才公告\">数字重庆信息技术服务有限公司2023年市场化招聘专业人才公告</a>\n                                </h5>\n                                <time class=\"\">2023-08-18</time>\n                            </li>\n                                                    <li>\n                                <h5>\n                                    <i class=\"notice-label\">[大足区]</i>\n                                    <i class=\"notice-label\">[教师]</i>\n                                    \n                                    <a href=\"https://www.gongkaoleida.com/article/1607893\" target=\"_blank\" title=\"重庆市大足区教育事业单位面向公费师范生考核招聘工作人员公告\">重庆市大足区教育事业单位面向公费师范生考核招聘工作人员公告</a>\n                                </h5>\n                                <time class=\"\">2023-08-18</time>\n                            </li>\n                                                    <li>\n                                <h5>\n                                    <i class=\"notice-label\">[重庆市]</i>\n                                    <i class=\"notice-label\">[国企]</i>\n                                    \n                                    <a href=\"https://www.gongkaoleida.com/article/1607718\" target=\"_blank\" title=\"重庆建工市政基础设施工程事业部招聘启事\">重庆建工市政基础设施工程事业部招聘启事</a>\n                                </h5>\n                                <time class=\"\">2023-08-18</time>\n                            </li>\n                                                    <li>\n                                <h5>\n                                    <i class=\"notice-label\">[綦江区]</i>\n                                    <i class=\"notice-label\">[国企]</i>\n                                    \n                                    <a href=\"https://www.gongkaoleida.com/article/1607715\" target=\"_blank\" title=\"重庆建工高新建材有限公司招聘启事\">重庆建工高新建材有限公司招聘启事</a>\n                                </h5>\n                                <time class=\"\">2023-08-18</time>\n                            </li>\n                                                    <li>\n                                <h5>\n                                    <i class=\"notice-label\">[渝北区]</i>\n                                    <i class=\"notice-label\">[事业单位]</i>\n                                    \n                                    <a href=\"https://www.gongkaoleida.com/article/1607381\" target=\"_blank\" title=\"渝北区玉峰山镇机关临聘人员招聘简章\">渝北区玉峰山镇机关临聘人员招聘简章</a>\n                                </h5>\n                                <time class=\"\">2023-08-18</time>\n                            </li>\n                                                    <li>\n                                <h5>\n                                    <i class=\"notice-label\">[大足区]</i>\n                                    <i class=\"notice-label\">[事业单位]</i>\n                                    \n                                    <a href=\"https://www.gongkaoleida.com/article/1606771\" target=\"_blank\" title=\"重庆飞驶特人力资源管理有限公司大足分公司派往重庆市大足区文化和旅游发展委员会招聘启事\">重庆飞驶特人力资源管理有限公司大足分公司派往重庆市大足区文化和旅游发展委员会招聘启事</a>\n                                </h5>\n                                <time class=\"\">2023-08-17</time>\n                            </li>\n                                            </ul>\n                </div>\n                <div class=\"pagelist-box\">\n    <ul class=\"pagelist clearfix\">\n\n                    <li class=\"disabled\"><a href=\"javascript:;\">首页</a></li>\n            <li class=\"disabled\"><a href=\"javascript:;\">上一页</a></li>\n        \n                    <li><a href=\"/area/2460-2461-0-2,3,59,78-124?page=1\" class=\"list-num  list-active \">1</a></li>\n                    <li><a href=\"/area/2460-2461-0-2,3,59,78-124?page=2\" class=\"list-num \">2</a></li>\n                    <li><a href=\"/area/2460-2461-0-2,3,59,78-124?page=3\" class=\"list-num \">3</a></li>\n                    <li><a href=\"/area/2460-2461-0-2,3,59,78-124?page=4\" class=\"list-num \">4</a></li>\n                    <li><a href=\"/area/2460-2461-0-2,3,59,78-124?page=5\" class=\"list-num \">5</a></li>\n                    <li><a href=\"/area/2460-2461-0-2,3,59,78-124?page=6\" class=\"list-num \">6</a></li>\n                    <li><a href=\"/area/2460-2461-0-2,3,59,78-124?page=7\" class=\"list-num \">7</a></li>\n        \n                    <li class=\"pagelist-ellipsis\"><span>···</span></li>\n            <li><a href=\"/area/2460-2461-0-2,3,59,78-124?page=207\" class=\"list-num\">207</a></li>\n        \n                    <li><a href=\"/area/2460-2461-0-2,3,59,78-124?page=2\">下一页</a></li>\n            <li><a href=\"/area/2460-2461-0-2,3,59,78-124?page=207\">尾页</a></li>\n        \n    </ul>\n</div>","link":"https://www.gongkaoleida.com/article/1615047","retrieved":1692768758250}]}